README.rst
setup.cfg
setup.py
dataify/__init__.py
dataify/brats.py
dataify/dsprites.py
dataify/echocardiography.py
dataify/harmonic.py
dataify/hcp.py
dataify/impac.py
dataify/info.py
dataify/kang.py
dataify/moving_mnist.py
dataify.egg-info/PKG-INFO
dataify.egg-info/SOURCES.txt
dataify.egg-info/dependency_links.txt
dataify.egg-info/requires.txt
dataify.egg-info/top_level.txt
dataify/tests/test_dsprites.py
dataify/tests/test_echocardiography.py
dataify/tests/test_harmonic.py
dataify/tests/test_impac.py
dataify/tests/test_kang.py
dataify/tests/test_moving_mnist.py