Metadata-Version: 1.1
Name: dataify
Version: 0.0.0
Summary: 
